{
  "id": "LJKdKKuzCQSLAJ9",
  "unique_key": "https://www.hsbc.com.hk/en-hk/ways-to-bank/internet/security-key",
  "order_no": null,
  "handled_at": "2025-02-20 11:02:52.483916+00:00",
  "request": {
    "url": "https://www.hsbc.com.hk/en-hk/ways-to-bank/internet/security-key/#280243968__tab0",
    "method": "GET",
    "headers": {},
    "payload": null,
    "user_data": {
      "__crawlee": {
        "state": 3,
        "crawlDepth": 1
      }
    },
    "retry_count": 0,
    "no_retry": false,
    "loaded_url": "https://www.hsbc.com.hk/en-hk/ways-to-bank/internet/security-key/#280243968__tab0",
    "handled_at": "2025-02-20 11:02:52.483916+00:00",
    "unique_key": "https://www.hsbc.com.hk/en-hk/ways-to-bank/internet/security-key",
    "id": "LJKdKKuzCQSLAJ9"
  }
}