{
  "id": "oa9J3HAcEgwyjpO",
  "unique_key": "https://www.hsbc.com.hk/content/dam/hsbc/hk/vam/pdf/ibb_getinsuredonlinechallenge_jun2024_tc_sc.pdf",
  "order_no": null,
  "handled_at": "2025-02-20 12:43:08.913187+00:00",
  "request": {
    "url": "https://www.hsbc.com.hk/content/dam/hsbc/hk/vam/pdf/IBB_GetInsuredOnlineChallenge_Jun2024_TC_SC.pdf",
    "method": "GET",
    "headers": {},
    "payload": null,
    "user_data": {
      "__crawlee": {
        "state": 5,
        "crawlDepth": 3
      }
    },
    "retry_count": 2,
    "no_retry": false,
    "loaded_url": null,
    "handled_at": "2025-02-20 12:43:08.913187+00:00",
    "unique_key": "https://www.hsbc.com.hk/content/dam/hsbc/hk/vam/pdf/ibb_getinsuredonlinechallenge_jun2024_tc_sc.pdf",
    "id": "oa9J3HAcEgwyjpO"
  }
}