{
  "id": "rjk09gbganO0uzh",
  "unique_key": "https://www.hsbc.com.hk/zh-cn/investments/products/mutual-funds/flexinvest/list",
  "order_no": null,
  "handled_at": "2025-02-20 12:24:45.530871+00:00",
  "request": {
    "url": "https://www.hsbc.com.hk/zh-cn/investments/products/mutual-funds/flexinvest/list/#money-market-funds",
    "method": "GET",
    "headers": {},
    "payload": null,
    "user_data": {
      "__crawlee": {
        "state": 3,
        "crawlDepth": 2
      }
    },
    "retry_count": 0,
    "no_retry": false,
    "loaded_url": "https://www.hsbc.com.hk/zh-cn/investments/products/mutual-funds/flexinvest/list/#money-market-funds",
    "handled_at": "2025-02-20 12:24:45.530871+00:00",
    "unique_key": "https://www.hsbc.com.hk/zh-cn/investments/products/mutual-funds/flexinvest/list",
    "id": "rjk09gbganO0uzh"
  }
}