{
  "id": "z5bzOoi5cXkRiaS",
  "unique_key": "https://www.hsbc.com.hk/zh-cn/insurance/terms/accidhighlights",
  "order_no": null,
  "handled_at": "2025-02-20 12:38:08.936576+00:00",
  "request": {
    "url": "https://www.hsbc.com.hk/zh-cn/insurance/terms/Accidhighlights/",
    "method": "GET",
    "headers": {},
    "payload": null,
    "user_data": {
      "__crawlee": {
        "state": 3,
        "crawlDepth": 4
      }
    },
    "retry_count": 0,
    "no_retry": false,
    "loaded_url": "https://www.hsbc.com.hk/zh-cn/insurance/terms/Accidhighlights/",
    "handled_at": "2025-02-20 12:38:08.936576+00:00",
    "unique_key": "https://www.hsbc.com.hk/zh-cn/insurance/terms/accidhighlights",
    "id": "z5bzOoi5cXkRiaS"
  }
}