{
  "id": "1kWyM9iy30SYZi1",
  "unique_key": "https://www.hsbc.com.hk/zh-hk/mpf/regular-withdrawal-for-retirement",
  "order_no": null,
  "handled_at": "2025-02-20 11:14:04.114695+00:00",
  "request": {
    "url": "https://www.hsbc.com.hk/zh-hk/mpf/regular-withdrawal-for-retirement/",
    "method": "GET",
    "headers": {},
    "payload": null,
    "user_data": {
      "__crawlee": {
        "state": 3,
        "crawlDepth": 2
      }
    },
    "retry_count": 0,
    "no_retry": false,
    "loaded_url": "https://www.hsbc.com.hk/zh-hk/mpf/regular-withdrawal-for-retirement/",
    "handled_at": "2025-02-20 11:14:04.114695+00:00",
    "unique_key": "https://www.hsbc.com.hk/zh-hk/mpf/regular-withdrawal-for-retirement",
    "id": "1kWyM9iy30SYZi1"
  }
}