{
  "id": "hpjcmQcg6VIcURB",
  "unique_key": "https://www.hsbc.com.hk/pws/components/common/app-redirect/mobileapp.html?lang=tc&pid=text__pws_tc_dcm94600",
  "order_no": null,
  "handled_at": "2025-02-20 11:40:38.574162+00:00",
  "request": {
    "url": "https://www.hsbc.com.hk/pws/Components/common/app-redirect/mobileapp.html?lang=tc&pid=TEXT__PWS_TC_DCM94600",
    "method": "GET",
    "headers": {},
    "payload": null,
    "user_data": {
      "__crawlee": {
        "state": 3,
        "crawlDepth": 2
      }
    },
    "retry_count": 0,
    "no_retry": false,
    "loaded_url": "https://www.hsbc.com.hk/zh-hk/campaigns/prom189/?pid=TEXT__PWS_TC_DCM94600",
    "handled_at": "2025-02-20 11:40:38.574162+00:00",
    "unique_key": "https://www.hsbc.com.hk/pws/components/common/app-redirect/mobileapp.html?lang=tc&pid=text__pws_tc_dcm94600",
    "id": "hpjcmQcg6VIcURB"
  }
}